repopulator/__init__.py
repopulator/__main__.py
repopulator/alpine.py
repopulator/apt.py
repopulator/freebsd.py
repopulator/pacman.py
repopulator/pgp_signer.py
repopulator/pki_signer.py
repopulator/py.typed
repopulator/rpm.py
repopulator/util.py
repopulator/version.py
repopulator-1.6.dist-info/licenses/LICENSE.txt
repopulator-1.6.dist-info/METADATA
repopulator-1.6.dist-info/WHEEL
repopulator-1.6.dist-info/entry_points.txt
repopulator-1.6.dist-info/top_level.txt
repopulator-1.6.dist-info/RECORD
