Metadata-Version: 2.4
Name: repopulator
Version: 1.6
Summary: A portable library to generate binary software repositories
Author-email: Eugene Gershnik <gershnik@hotmail.com>
License-Expression: BSD-3-Clause
Project-URL: Homepage, https://github.com/gershnik/repopulator
Project-URL: Documentation, https://gershnik.github.io/repopulator
Project-URL: Issues, https://github.com/gershnik/repopulator/issues
Project-URL: Changelog, https://github.com/gershnik/repopulator/blob/master/CHANGELOG.md
Keywords: cross-platform,apt-repository,yum-repositories,freebsd-packages,rpm-repositories,apt-repo,yum-repos,pacman-repo,alpine-repository
Classifier: Development Status :: 5 - Production/Stable
Classifier: Operating System :: OS Independent
Classifier: Intended Audience :: Developers
Classifier: Intended Audience :: System Administrators
Classifier: Topic :: System
Classifier: Topic :: System :: Archiving :: Packaging
Classifier: Topic :: System :: Software Distribution
Classifier: Topic :: Software Development :: Libraries
Classifier: Topic :: Utilities
Classifier: Programming Language :: Python
Classifier: Programming Language :: Python :: 3
Classifier: Programming Language :: Python :: 3.9
Classifier: Programming Language :: Python :: 3.10
Classifier: Programming Language :: Python :: 3.11
Classifier: Programming Language :: Python :: 3.12
Classifier: Programming Language :: Python :: 3.13
Classifier: Typing :: Typed
Requires-Python: >=3.9
License-File: LICENSE.txt
Requires-Dist: rpmfile>=2.1.0
Requires-Dist: arpy>=2.3.0
Requires-Dist: cryptography>=43.0.1
Requires-Dist: zstandard[cffi]>=0.23.0
Dynamic: license-file
